{"data_mtime": 1605049417, "dep_lines": [3, 4, 1], "dep_prios": [5, 5, 5], "dependencies": ["email.charset", "typing", "builtins"], "hash": "9e43e8ff946dfe070ec278f497c1af6ae9880ac76c0d337c6d6a8d3c2e78df25", "id": "email.header", "ignore_all": true, "interface_hash": "cc3e9cfcb1bd3f0a584aa514d579e73609375ce95f140baef491e4b41a536224", "mtime": 1605049335, "options": {"allow_redefinition": false, "allow_untyped_globals": false, "always_false": [], "always_true": [], "bazel": false, "check_untyped_defs": false, "disallow_any_decorated": false, "disallow_any_explicit": false, "disallow_any_expr": false, "disallow_any_generics": false, "disallow_any_unimported": false, "disallow_incomplete_defs": false, "disallow_subclassing_any": false, "disallow_untyped_calls": false, "disallow_untyped_decorators": false, "disallow_untyped_defs": false, "follow_imports": "silent", "follow_imports_for_stubs": false, "ignore_errors": false, "ignore_missing_imports": true, "implicit_reexport": true, "local_partial_types": false, "mypyc": false, "no_implicit_optional": false, "platform": "win32", "plugins": [], "show_none_errors": true, "strict_equality": false, "strict_optional": true, "strict_optional_whitelist": null, "warn_no_return": true, "warn_return_any": false, "warn_unreachable": false, "warn_unused_ignores": false}, "path": "C:\\Users\\others\\AppData\\Roaming\\Python\\Python38\\site-packages\\mypy\\typeshed\\stdlib\\3\\email\\header.pyi", "plugin_data": null, "size": 1064, "suppressed": [], "version_id": "0.790"}